{
  "collectionName": "components_sections_app_intros",
  "info": {
    "name": "appIntro",
    "icon": "address-card",
    "description": ""
  },
  "options": {},
  "attributes": {
    "title": {
      "type": "string"
    },
    "description": {
      "type": "text"
    },
    "image": {
      "model": "file",
      "via": "related",
      "allowedTypes": [
        "images",
        "files",
        "videos"
      ],
      "plugin": "upload",
      "required": false,
      "pluginOptions": {}
    }
  }
}
